sirchmunk/__init__.py
sirchmunk/base.py
sirchmunk/search.py
sirchmunk/version.py
sirchmunk/insight/__init__.py
sirchmunk/insight/text_insights.py
sirchmunk/learnings/__init__.py
sirchmunk/learnings/evidence_processor.py
sirchmunk/learnings/knowledge_base.py
sirchmunk/llm/__init__.py
sirchmunk/llm/openai_chat.py
sirchmunk/llm/prompts.py
sirchmunk/retrieve/__init__.py
sirchmunk/retrieve/base.py
sirchmunk/retrieve/text_retriever.py
sirchmunk/scan/__init__.py
sirchmunk/scan/base.py
sirchmunk/scan/file_scanner.py
sirchmunk/scan/web_scanner.py
sirchmunk/scheduler/__init__.py
sirchmunk/schema/__init__.py
sirchmunk/schema/cognition.py
sirchmunk/schema/context.py
sirchmunk/schema/knowledge.py
sirchmunk/schema/metadata.py
sirchmunk/schema/request.py
sirchmunk/schema/response.py
sirchmunk/schema/snapshot.py
sirchmunk/storage/__init__.py
sirchmunk/storage/duckdb.py
sirchmunk/storage/knowledge_manager.py
sirchmunk/utils/__init__.py
sirchmunk/utils/constants.py
sirchmunk/utils/deps.py
sirchmunk/utils/file_utils.py
sirchmunk/utils/install_rga.py
sirchmunk/utils/log_utils.py
sirchmunk/utils/tokenizer_util.py
sirchmunk/utils/utils.py
sirchmunk-0.0.1.post1.dist-info/licenses/LICENSE
sirchmunk-0.0.1.post1.dist-info/METADATA
sirchmunk-0.0.1.post1.dist-info/WHEEL
sirchmunk-0.0.1.post1.dist-info/entry_points.txt
sirchmunk-0.0.1.post1.dist-info/top_level.txt
sirchmunk-0.0.1.post1.dist-info/RECORD
