Metadata-Version: 2.4
Name: sirchmunk
Version: 0.0.1.post1
Summary: Sirchmunk: From raw data to self-evolving real-time intelligence.
Author: ModelScope Team
Author-email: contact@modelscope.cn
License: Apache License 2.0
Project-URL: Homepage, https://github.com/modelscope/sirchmunk
Keywords: LLM,Agentic Search,Embedding-Free,RAG,Indexless,Self-evolving,Real-time Intelligence,Multi-modal
Classifier: Development Status :: 4 - Beta
Classifier: Operating System :: OS Independent
Classifier: Programming Language :: Python :: 3
Classifier: Programming Language :: Python :: 3.10
Classifier: Programming Language :: Python :: 3.11
Classifier: Programming Language :: Python :: 3.12
Classifier: Programming Language :: Python :: 3.13
Classifier: Programming Language :: Python :: 3.14
Classifier: License :: OSI Approved :: Apache Software License
Requires-Python: >=3.10
License-File: LICENSE
Requires-Dist: loguru
Requires-Dist: fastapi
Requires-Dist: openai
Requires-Dist: genson
Requires-Dist: pillow
Requires-Dist: pypdf
Requires-Dist: pandas
Requires-Dist: parquet
Requires-Dist: numpy
Requires-Dist: msgpack
Requires-Dist: sentencepiece
Requires-Dist: tqdm
Requires-Dist: rapidfuzz
Requires-Dist: duckdb
Requires-Dist: kreuzberg>=4.0.0rc1
Provides-Extra: web
Requires-Dist: fastapi>=0.100.0; extra == "web"
Requires-Dist: uvicorn[standard]>=0.24.0; extra == "web"
Requires-Dist: websockets>=12.0; extra == "web"
Requires-Dist: python-multipart>=0.0.6; extra == "web"
Requires-Dist: pydantic>=2.0.0; extra == "web"
Requires-Dist: requests>=2.32.2; extra == "web"
Requires-Dist: aiohttp>=3.9.4; extra == "web"
Requires-Dist: httpx>=0.27.0; extra == "web"
Requires-Dist: urllib3>=2.2.1; extra == "web"
Requires-Dist: pydantic>=2.0; extra == "web"
Requires-Dist: python-dotenv>=1.0.0; extra == "web"
Requires-Dist: psutil; extra == "web"
Provides-Extra: docs
Requires-Dist: docutils>=0.16.0; extra == "docs"
Requires-Dist: myst_parser; extra == "docs"
Requires-Dist: recommonmark; extra == "docs"
Requires-Dist: sphinx>=5.3.0; extra == "docs"
Requires-Dist: sphinx-book-theme; extra == "docs"
Requires-Dist: sphinx-copybutton; extra == "docs"
Requires-Dist: sphinx-design; extra == "docs"
Requires-Dist: sphinx_markdown_tables; extra == "docs"
Requires-Dist: sphinxawesome-theme; extra == "docs"
Requires-Dist: sphinxcontrib-mermaid; extra == "docs"
Provides-Extra: tests
Requires-Dist: pytest; extra == "tests"
Requires-Dist: pytest-asyncio; extra == "tests"
Provides-Extra: all
Requires-Dist: fastapi>=0.100.0; extra == "all"
Requires-Dist: uvicorn[standard]>=0.24.0; extra == "all"
Requires-Dist: websockets>=12.0; extra == "all"
Requires-Dist: python-multipart>=0.0.6; extra == "all"
Requires-Dist: pydantic>=2.0.0; extra == "all"
Requires-Dist: requests>=2.32.2; extra == "all"
Requires-Dist: aiohttp>=3.9.4; extra == "all"
Requires-Dist: httpx>=0.27.0; extra == "all"
Requires-Dist: urllib3>=2.2.1; extra == "all"
Requires-Dist: pydantic>=2.0; extra == "all"
Requires-Dist: python-dotenv>=1.0.0; extra == "all"
Requires-Dist: psutil; extra == "all"
Requires-Dist: docutils>=0.16.0; extra == "all"
Requires-Dist: myst_parser; extra == "all"
Requires-Dist: recommonmark; extra == "all"
Requires-Dist: sphinx>=5.3.0; extra == "all"
Requires-Dist: sphinx-book-theme; extra == "all"
Requires-Dist: sphinx-copybutton; extra == "all"
Requires-Dist: sphinx-design; extra == "all"
Requires-Dist: sphinx_markdown_tables; extra == "all"
Requires-Dist: sphinxawesome-theme; extra == "all"
Requires-Dist: sphinxcontrib-mermaid; extra == "all"
Requires-Dist: pytest; extra == "all"
Requires-Dist: pytest-asyncio; extra == "all"
Dynamic: license-file
